{
  "script_id": "51_julie_intro",
  "dj": "julie",
  "content_type": "song_intro",
  "score": 8.75,
  "passed": true,
  "criteria_scores": {
    "character_voice": 9.0,
    "era_appropriateness": 10.0,
    "forbidden_elements": 10.0,
    "natural_flow": 7.0,
    "length": 5.0
  },
  "issues": [],
  "notes": "The script flows naturally, and the character's voice is consistent with the provided samples. It uses 1950s language and does not mention any dates or years. The length of the script is appropriate, and it ends with introducing the song. No issues found."
}